prompt_tool_kit/__init__.py
prompt_tool_kit/application.py
prompt_tool_kit/auto_suggest.py
prompt_tool_kit/buffer.py
prompt_tool_kit/buffer_mapping.py
prompt_tool_kit/cache.py
prompt_tool_kit/completion.py
prompt_tool_kit/document.py
prompt_tool_kit/enums.py
prompt_tool_kit/history.py
prompt_tool_kit/input.py
prompt_tool_kit/interface.py
prompt_tool_kit/keys.py
prompt_tool_kit/mouse_events.py
prompt_tool_kit/output.py
prompt_tool_kit/reactive.py
prompt_tool_kit/renderer.py
prompt_tool_kit/search_state.py
prompt_tool_kit/selection.py
prompt_tool_kit/shortcuts.py
prompt_tool_kit/token.py
prompt_tool_kit/utils.py
prompt_tool_kit/validation.py
prompt_tool_kit/win32_types.py
prompt_tool_kit/clipboard/__init__.py
prompt_tool_kit/clipboard/base.py
prompt_tool_kit/clipboard/in_memory.py
prompt_tool_kit/clipboard/pyperclip.py
prompt_tool_kit/contrib/__init__.py
prompt_tool_kit/contrib/completers/__init__.py
prompt_tool_kit/contrib/completers/base.py
prompt_tool_kit/contrib/completers/filesystem.py
prompt_tool_kit/contrib/completers/system.py
prompt_tool_kit/contrib/regular_languages/__init__.py
prompt_tool_kit/contrib/regular_languages/compiler.py
prompt_tool_kit/contrib/regular_languages/completion.py
prompt_tool_kit/contrib/regular_languages/lexer.py
prompt_tool_kit/contrib/regular_languages/regex_parser.py
prompt_tool_kit/contrib/regular_languages/validation.py
prompt_tool_kit/contrib/telnet/__init__.py
prompt_tool_kit/contrib/telnet/application.py
prompt_tool_kit/contrib/telnet/log.py
prompt_tool_kit/contrib/telnet/protocol.py
prompt_tool_kit/contrib/telnet/server.py
prompt_tool_kit/contrib/validators/__init__.py
prompt_tool_kit/contrib/validators/base.py
prompt_tool_kit/eventloop/__init__.py
prompt_tool_kit/eventloop/asyncio_base.py
prompt_tool_kit/eventloop/asyncio_posix.py
prompt_tool_kit/eventloop/asyncio_win32.py
prompt_tool_kit/eventloop/base.py
prompt_tool_kit/eventloop/callbacks.py
prompt_tool_kit-1.0.14.dist-info/DESCRIPTION.rst
prompt_tool_kit-1.0.14.dist-info/METADATA
prompt_tool_kit-1.0.14.dist-info/RECORD
prompt_tool_kit-1.0.14.dist-info/WHEEL
prompt_tool_kit-1.0.14.dist-info/metadata.json
prompt_tool_kit-1.0.14.dist-info/top_level.txt
