Metadata-Version: 2.0
Name: prompt-tool-kit
Version: 1.0.14
Summary: Library for building powerful interactive command lines in Python
Home-page: https://github.com/jonathanslenders/python-prompt-toolkit
Author: Jonathan Slenders
Author-email: UNKNOWN
License: UNKNOWN
Platform: UNKNOWN
Classifier: Development Status :: 5 - Production/Stable
Classifier: Intended Audience :: Developers
Classifier: License :: OSI Approved :: BSD License
Classifier: Operating System :: OS Independent
Classifier: Programming Language :: Python :: 2
Classifier: Programming Language :: Python :: 2.6
Classifier: Programming Language :: Python :: 2.7
Classifier: Programming Language :: Python :: 3
Classifier: Programming Language :: Python :: 3.3
Classifier: Programming Language :: Python :: 3.4
Classifier: Programming Language :: Python :: 3.5
Classifier: Programming Language :: Python
Classifier: Topic :: Software Development
Requires-Dist: six (>=1.9.0)
Requires-Dist: wcwidth
